LICENSE
readme.md
trim21_flexget_plugins/modify/magnet_add_dn.py
trim21_flexget_plugins-0.0.3.dist-info/entry_points.txt
trim21_flexget_plugins-0.0.3.dist-info/LICENSE
trim21_flexget_plugins-0.0.3.dist-info/WHEEL
trim21_flexget_plugins-0.0.3.dist-info/METADATA
trim21_flexget_plugins-0.0.3.dist-info/RECORD
